{
  "id": 475,
  "args_num": 2,
  "info": "若造成的伤害不足{0}，则下{1}回合的攻击必定致命一击",
  "info_formatting_adjustment": null,
  "analyze_info": "[sprite name=iconHit]若造成的伤害不足{0}，则下{1}回合的攻击必定[color=#57c975]致命一击[/color]（boss有效）",
  "pve_effective": true,
  "param": null,
  "skill": [
    {
      "id": 14118,
      "url": "https://api.seerapi.com/v1/skill/14118"
    },
    {
      "id": 14592,
      "url": "https://api.seerapi.com/v1/skill/14592"
    },
    {
      "id": 15918,
      "url": "https://api.seerapi.com/v1/skill/15918"
    },
    {
      "id": 16880,
      "url": "https://api.seerapi.com/v1/skill/16880"
    },
    {
      "id": 17162,
      "url": "https://api.seerapi.com/v1/skill/17162"
    },
    {
      "id": 17191,
      "url": "https://api.seerapi.com/v1/skill/17191"
    },
    {
      "id": 17458,
      "url": "https://api.seerapi.com/v1/skill/17458"
    },
    {
      "id": 17540,
      "url": "https://api.seerapi.com/v1/skill/17540"
    },
    {
      "id": 17698,
      "url": "https://api.seerapi.com/v1/skill/17698"
    },
    {
      "id": 19149,
      "url": "https://api.seerapi.com/v1/skill/19149"
    },
    {
      "id": 19496,
      "url": "https://api.seerapi.com/v1/skill/19496"
    },
    {
      "id": 19570,
      "url": "https://api.seerapi.com/v1/skill/19570"
    },
    {
      "id": 19805,
      "url": "https://api.seerapi.com/v1/skill/19805"
    },
    {
      "id": 19811,
      "url": "https://api.seerapi.com/v1/skill/19811"
    },
    {
      "id": 30076,
      "url": "https://api.seerapi.com/v1/skill/30076"
    },
    {
      "id": 30155,
      "url": "https://api.seerapi.com/v1/skill/30155"
    },
    {
      "id": 30173,
      "url": "https://api.seerapi.com/v1/skill/30173"
    },
    {
      "id": 30374,
      "url": "https://api.seerapi.com/v1/skill/30374"
    },
    {
      "id": 30453,
      "url": "https://api.seerapi.com/v1/skill/30453"
    },
    {
      "id": 30640,
      "url": "https://api.seerapi.com/v1/skill/30640"
    },
    {
      "id": 30911,
      "url": "https://api.seerapi.com/v1/skill/30911"
    },
    {
      "id": 30917,
      "url": "https://api.seerapi.com/v1/skill/30917"
    },
    {
      "id": 31699,
      "url": "https://api.seerapi.com/v1/skill/31699"
    },
    {
      "id": 31941,
      "url": "https://api.seerapi.com/v1/skill/31941"
    },
    {
      "id": 32210,
      "url": "https://api.seerapi.com/v1/skill/32210"
    },
    {
      "id": 32304,
      "url": "https://api.seerapi.com/v1/skill/32304"
    },
    {
      "id": 32431,
      "url": "https://api.seerapi.com/v1/skill/32431"
    },
    {
      "id": 32436,
      "url": "https://api.seerapi.com/v1/skill/32436"
    },
    {
      "id": 32543,
      "url": "https://api.seerapi.com/v1/skill/32543"
    },
    {
      "id": 32560,
      "url": "https://api.seerapi.com/v1/skill/32560"
    },
    {
      "id": 32582,
      "url": "https://api.seerapi.com/v1/skill/32582"
    },
    {
      "id": 32695,
      "url": "https://api.seerapi.com/v1/skill/32695"
    },
    {
      "id": 32725,
      "url": "https://api.seerapi.com/v1/skill/32725"
    },
    {
      "id": 33327,
      "url": "https://api.seerapi.com/v1/skill/33327"
    },
    {
      "id": 33463,
      "url": "https://api.seerapi.com/v1/skill/33463"
    },
    {
      "id": 33932,
      "url": "https://api.seerapi.com/v1/skill/33932"
    },
    {
      "id": 34229,
      "url": "https://api.seerapi.com/v1/skill/34229"
    },
    {
      "id": 34360,
      "url": "https://api.seerapi.com/v1/skill/34360"
    },
    {
      "id": 34726,
      "url": "https://api.seerapi.com/v1/skill/34726"
    },
    {
      "id": 35039,
      "url": "https://api.seerapi.com/v1/skill/35039"
    },
    {
      "id": 35069,
      "url": "https://api.seerapi.com/v1/skill/35069"
    },
    {
      "id": 35186,
      "url": "https://api.seerapi.com/v1/skill/35186"
    },
    {
      "id": 35369,
      "url": "https://api.seerapi.com/v1/skill/35369"
    },
    {
      "id": 35378,
      "url": "https://api.seerapi.com/v1/skill/35378"
    },
    {
      "id": 35495,
      "url": "https://api.seerapi.com/v1/skill/35495"
    },
    {
      "id": 36444,
      "url": "https://api.seerapi.com/v1/skill/36444"
    },
    {
      "id": 36877,
      "url": "https://api.seerapi.com/v1/skill/36877"
    },
    {
      "id": 37027,
      "url": "https://api.seerapi.com/v1/skill/37027"
    },
    {
      "id": 38038,
      "url": "https://api.seerapi.com/v1/skill/38038"
    },
    {
      "id": 38449,
      "url": "https://api.seerapi.com/v1/skill/38449"
    }
  ],
  "tag": [
    {
      "id": 8553,
      "url": "https://api.seerapi.com/v1/skill_effect_type_tag/8553"
    }
  ],
  "hash": "c1200ba8"
}