{
  "type": {
    "id": 3,
    "url": "https://api.seerapi.com/v1/mintmark_type/3"
  },
  "rarity": {
    "id": 1,
    "url": "https://api.seerapi.com/v1/mintmark_rarity/1"
  },
  "pet": [
    {
      "id": 3328,
      "url": "https://api.seerapi.com/v1/pet/3328"
    }
  ],
  "id": 40874,
  "name": "圣王·萨格罗斯专属全能刻印",
  "desc": "体力10/90,攻击5/50,防御6/30,特防6/30,速度3/30",
  "mintmark_class": null,
  "base_attr_value": {
    "atk": 5,
    "def": 6,
    "sp_atk": 0,
    "sp_def": 6,
    "spd": 3,
    "hp": 10,
    "percent": false,
    "total": 30
  },
  "max_attr_value": {
    "atk": 50,
    "def": 30,
    "sp_atk": 0,
    "sp_def": 30,
    "spd": 30,
    "hp": 90,
    "percent": false,
    "total": 230
  },
  "extra_attr_value": null,
  "connect": null,
  "is_hidden": false,
  "hash": "42fbbf10"
}