{
  "count": 138,
  "next": null,
  "previous": null,
  "first": null,
  "last": null,
  "results": [
    {
      "id": 1,
      "url": "https://api.seerapi.com/v1/element_type_combination/1",
      "name": "草"
    },
    {
      "id": 2,
      "url": "https://api.seerapi.com/v1/element_type_combination/2",
      "name": "水"
    },
    {
      "id": 3,
      "url": "https://api.seerapi.com/v1/element_type_combination/3",
      "name": "火"
    },
    {
      "id": 4,
      "url": "https://api.seerapi.com/v1/element_type_combination/4",
      "name": "飞行"
    },
    {
      "id": 5,
      "url": "https://api.seerapi.com/v1/element_type_combination/5",
      "name": "电"
    },
    {
      "id": 6,
      "url": "https://api.seerapi.com/v1/element_type_combination/6",
      "name": "机械"
    },
    {
      "id": 7,
      "url": "https://api.seerapi.com/v1/element_type_combination/7",
      "name": "地面"
    },
    {
      "id": 8,
      "url": "https://api.seerapi.com/v1/element_type_combination/8",
      "name": "普通"
    },
    {
      "id": 9,
      "url": "https://api.seerapi.com/v1/element_type_combination/9",
      "name": "冰"
    },
    {
      "id": 10,
      "url": "https://api.seerapi.com/v1/element_type_combination/10",
      "name": "超能"
    },
    {
      "id": 11,
      "url": "https://api.seerapi.com/v1/element_type_combination/11",
      "name": "战斗"
    },
    {
      "id": 12,
      "url": "https://api.seerapi.com/v1/element_type_combination/12",
      "name": "光"
    },
    {
      "id": 13,
      "url": "https://api.seerapi.com/v1/element_type_combination/13",
      "name": "暗影"
    },
    {
      "id": 14,
      "url": "https://api.seerapi.com/v1/element_type_combination/14",
      "name": "神秘"
    },
    {
      "id": 15,
      "url": "https://api.seerapi.com/v1/element_type_combination/15",
      "name": "龙"
    },
    {
      "id": 16,
      "url": "https://api.seerapi.com/v1/element_type_combination/16",
      "name": "圣灵"
    },
    {
      "id": 17,
      "url": "https://api.seerapi.com/v1/element_type_combination/17",
      "name": "次元"
    },
    {
      "id": 18,
      "url": "https://api.seerapi.com/v1/element_type_combination/18",
      "name": "远古"
    },
    {
      "id": 19,
      "url": "https://api.seerapi.com/v1/element_type_combination/19",
      "name": "邪灵"
    },
    {
      "id": 20,
      "url": "https://api.seerapi.com/v1/element_type_combination/20",
      "name": "自然"
    },
    {
      "id": 21,
      "url": "https://api.seerapi.com/v1/element_type_combination/21",
      "name": "草 超能"
    },
    {
      "id": 22,
      "url": "https://api.seerapi.com/v1/element_type_combination/22",
      "name": "草 战斗"
    },
    {
      "id": 23,
      "url": "https://api.seerapi.com/v1/element_type_combination/23",
      "name": "草 暗影"
    },
    {
      "id": 24,
      "url": "https://api.seerapi.com/v1/element_type_combination/24",
      "name": "水 超能"
    },
    {
      "id": 25,
      "url": "https://api.seerapi.com/v1/element_type_combination/25",
      "name": "水 暗影"
    },
    {
      "id": 26,
      "url": "https://api.seerapi.com/v1/element_type_combination/26",
      "name": "水 龙"
    },
    {
      "id": 27,
      "url": "https://api.seerapi.com/v1/element_type_combination/27",
      "name": "火 飞行"
    },
    {
      "id": 28,
      "url": "https://api.seerapi.com/v1/element_type_combination/28",
      "name": "火 龙"
    },
    {
      "id": 29,
      "url": "https://api.seerapi.com/v1/element_type_combination/29",
      "name": "火 超能"
    },
    {
      "id": 30,
      "url": "https://api.seerapi.com/v1/element_type_combination/30",
      "name": "飞行 超能"
    },
    {
      "id": 31,
      "url": "https://api.seerapi.com/v1/element_type_combination/31",
      "name": "光 飞行"
    },
    {
      "id": 32,
      "url": "https://api.seerapi.com/v1/element_type_combination/32",
      "name": "飞行 龙"
    },
    {
      "id": 33,
      "url": "https://api.seerapi.com/v1/element_type_combination/33",
      "name": "电 火"
    },
    {
      "id": 34,
      "url": "https://api.seerapi.com/v1/element_type_combination/34",
      "name": "电 冰"
    },
    {
      "id": 35,
      "url": "https://api.seerapi.com/v1/element_type_combination/35",
      "name": "电 战斗"
    },
    {
      "id": 36,
      "url": "https://api.seerapi.com/v1/element_type_combination/36",
      "name": "暗影 电"
    },
    {
      "id": 37,
      "url": "https://api.seerapi.com/v1/element_type_combination/37",
      "name": "机械 地面"
    },
    {
      "id": 38,
      "url": "https://api.seerapi.com/v1/element_type_combination/38",
      "name": "机械 超能"
    },
    {
      "id": 39,
      "url": "https://api.seerapi.com/v1/element_type_combination/39",
      "name": "机械 龙"
    },
    {
      "id": 40,
      "url": "https://api.seerapi.com/v1/element_type_combination/40",
      "name": "地面 龙"
    },
    {
      "id": 41,
      "url": "https://api.seerapi.com/v1/element_type_combination/41",
      "name": "战斗 地面"
    },
    {
      "id": 42,
      "url": "https://api.seerapi.com/v1/element_type_combination/42",
      "name": "地面 暗影"
    },
    {
      "id": 43,
      "url": "https://api.seerapi.com/v1/element_type_combination/43",
      "name": "冰 龙"
    },
    {
      "id": 44,
      "url": "https://api.seerapi.com/v1/element_type_combination/44",
      "name": "冰 光"
    },
    {
      "id": 45,
      "url": "https://api.seerapi.com/v1/element_type_combination/45",
      "name": "冰 暗影"
    },
    {
      "id": 46,
      "url": "https://api.seerapi.com/v1/element_type_combination/46",
      "name": "超能 冰"
    },
    {
      "id": 47,
      "url": "https://api.seerapi.com/v1/element_type_combination/47",
      "name": "战斗 火"
    },
    {
      "id": 48,
      "url": "https://api.seerapi.com/v1/element_type_combination/48",
      "name": "战斗 暗影"
    },
    {
      "id": 49,
      "url": "https://api.seerapi.com/v1/element_type_combination/49",
      "name": "光 神秘"
    },
    {
      "id": 50,
      "url": "https://api.seerapi.com/v1/element_type_combination/50",
      "name": "暗影 神秘"
    },
    {
      "id": 51,
      "url": "https://api.seerapi.com/v1/element_type_combination/51",
      "name": "神秘 超能"
    },
    {
      "id": 52,
      "url": "https://api.seerapi.com/v1/element_type_combination/52",
      "name": "圣灵 光"
    },
    {
      "id": 53,
      "url": "https://api.seerapi.com/v1/element_type_combination/53",
      "name": "飞行 神秘"
    },
    {
      "id": 54,
      "url": "https://api.seerapi.com/v1/element_type_combination/54",
      "name": "地面 超能"
    },
    {
      "id": 55,
      "url": "https://api.seerapi.com/v1/element_type_combination/55",
      "name": "暗影 龙"
    },
    {
      "id": 56,
      "url": "https://api.seerapi.com/v1/element_type_combination/56",
      "name": "圣灵 暗影"
    },
    {
      "id": 57,
      "url": "https://api.seerapi.com/v1/element_type_combination/57",
      "name": "远古 战斗"
    },
    {
      "id": 58,
      "url": "https://api.seerapi.com/v1/element_type_combination/58",
      "name": "火 神秘"
    },
    {
      "id": 59,
      "url": "https://api.seerapi.com/v1/element_type_combination/59",
      "name": "光 战斗"
    },
    {
      "id": 60,
      "url": "https://api.seerapi.com/v1/element_type_combination/60",
      "name": "神秘 战斗"
    },
    {
      "id": 61,
      "url": "https://api.seerapi.com/v1/element_type_combination/61",
      "name": "次元 战斗"
    },
    {
      "id": 62,
      "url": "https://api.seerapi.com/v1/element_type_combination/62",
      "name": "邪灵 神秘"
    },
    {
      "id": 63,
      "url": "https://api.seerapi.com/v1/element_type_combination/63",
      "name": "远古 龙"
    },
    {
      "id": 64,
      "url": "https://api.seerapi.com/v1/element_type_combination/64",
      "name": "光 次元"
    },
    {
      "id": 65,
      "url": "https://api.seerapi.com/v1/element_type_combination/65",
      "name": "远古 圣灵"
    },
    {
      "id": 66,
      "url": "https://api.seerapi.com/v1/element_type_combination/66",
      "name": "水 战斗"
    },
    {
      "id": 67,
      "url": "https://api.seerapi.com/v1/element_type_combination/67",
      "name": "电 龙"
    },
    {
      "id": 68,
      "url": "https://api.seerapi.com/v1/element_type_combination/68",
      "name": "光 火"
    },
    {
      "id": 69,
      "url": "https://api.seerapi.com/v1/element_type_combination/69",
      "name": "光 暗影"
    },
    {
      "id": 70,
      "url": "https://api.seerapi.com/v1/element_type_combination/70",
      "name": "邪灵 龙"
    },
    {
      "id": 71,
      "url": "https://api.seerapi.com/v1/element_type_combination/71",
      "name": "远古 神秘"
    },
    {
      "id": 72,
      "url": "https://api.seerapi.com/v1/element_type_combination/72",
      "name": "机械 次元"
    },
    {
      "id": 73,
      "url": "https://api.seerapi.com/v1/element_type_combination/73",
      "name": "战斗 龙"
    },
    {
      "id": 74,
      "url": "https://api.seerapi.com/v1/element_type_combination/74",
      "name": "战斗 自然"
    },
    {
      "id": 75,
      "url": "https://api.seerapi.com/v1/element_type_combination/75",
      "name": "邪灵 机械"
    },
    {
      "id": 76,
      "url": "https://api.seerapi.com/v1/element_type_combination/76",
      "name": "电 次元"
    },
    {
      "id": 77,
      "url": "https://api.seerapi.com/v1/element_type_combination/77",
      "name": "远古 火"
    },
    {
      "id": 78,
      "url": "https://api.seerapi.com/v1/element_type_combination/78",
      "name": "圣灵 战斗"
    },
    {
      "id": 79,
      "url": "https://api.seerapi.com/v1/element_type_combination/79",
      "name": "圣灵 次元"
    },
    {
      "id": 80,
      "url": "https://api.seerapi.com/v1/element_type_combination/80",
      "name": "圣灵 电"
    },
    {
      "id": 81,
      "url": "https://api.seerapi.com/v1/element_type_combination/81",
      "name": "远古 地面"
    },
    {
      "id": 82,
      "url": "https://api.seerapi.com/v1/element_type_combination/82",
      "name": "远古 草"
    },
    {
      "id": 83,
      "url": "https://api.seerapi.com/v1/element_type_combination/83",
      "name": "自然 龙"
    },
    {
      "id": 84,
      "url": "https://api.seerapi.com/v1/element_type_combination/84",
      "name": "冰 神秘"
    },
    {
      "id": 85,
      "url": "https://api.seerapi.com/v1/element_type_combination/85",
      "name": "飞行 暗影"
    },
    {
      "id": 86,
      "url": "https://api.seerapi.com/v1/element_type_combination/86",
      "name": "冰 火"
    },
    {
      "id": 87,
      "url": "https://api.seerapi.com/v1/element_type_combination/87",
      "name": "冰 飞行"
    },
    {
      "id": 88,
      "url": "https://api.seerapi.com/v1/element_type_combination/88",
      "name": "自然 圣灵"
    },
    {
      "id": 89,
      "url": "https://api.seerapi.com/v1/element_type_combination/89",
      "name": "混沌 圣灵"
    },
    {
      "id": 90,
      "url": "https://api.seerapi.com/v1/element_type_combination/90",
      "name": "远古 邪灵"
    },
    {
      "id": 91,
      "url": "https://api.seerapi.com/v1/element_type_combination/91",
      "name": "自然 冰"
    },
    {
      "id": 92,
      "url": "https://api.seerapi.com/v1/element_type_combination/92",
      "name": "混沌 暗影"
    },
    {
      "id": 93,
      "url": "https://api.seerapi.com/v1/element_type_combination/93",
      "name": "混沌 战斗"
    },
    {
      "id": 94,
      "url": "https://api.seerapi.com/v1/element_type_combination/94",
      "name": "混沌 超能"
    },
    {
      "id": 95,
      "url": "https://api.seerapi.com/v1/element_type_combination/95",
      "name": "圣灵 超能"
    },
    {
      "id": 96,
      "url": "https://api.seerapi.com/v1/element_type_combination/96",
      "name": "混沌 地面"
    },
    {
      "id": 97,
      "url": "https://api.seerapi.com/v1/element_type_combination/97",
      "name": "暗影 邪灵"
    },
    {
      "id": 98,
      "url": "https://api.seerapi.com/v1/element_type_combination/98",
      "name": "混沌 远古"
    },
    {
      "id": 99,
      "url": "https://api.seerapi.com/v1/element_type_combination/99",
      "name": "混沌 邪灵"
    },
    {
      "id": 100,
      "url": "https://api.seerapi.com/v1/element_type_combination/100",
      "name": "圣灵 地面"
    },
    {
      "id": 101,
      "url": "https://api.seerapi.com/v1/element_type_combination/101",
      "name": "火 暗影"
    },
    {
      "id": 102,
      "url": "https://api.seerapi.com/v1/element_type_combination/102",
      "name": "光 超能"
    },
    {
      "id": 103,
      "url": "https://api.seerapi.com/v1/element_type_combination/103",
      "name": "机械 战斗"
    },
    {
      "id": 104,
      "url": "https://api.seerapi.com/v1/element_type_combination/104",
      "name": "飞行 电"
    },
    {
      "id": 105,
      "url": "https://api.seerapi.com/v1/element_type_combination/105",
      "name": "混沌 飞行"
    },
    {
      "id": 106,
      "url": "https://api.seerapi.com/v1/element_type_combination/106",
      "name": "混沌 龙"
    },
    {
      "id": 107,
      "url": "https://api.seerapi.com/v1/element_type_combination/107",
      "name": "混沌 火"
    },
    {
      "id": 108,
      "url": "https://api.seerapi.com/v1/element_type_combination/108",
      "name": "圣灵 火"
    },
    {
      "id": 109,
      "url": "https://api.seerapi.com/v1/element_type_combination/109",
      "name": "地面 神秘"
    },
    {
      "id": 110,
      "url": "https://api.seerapi.com/v1/element_type_combination/110",
      "name": "混沌 次元"
    },
    {
      "id": 111,
      "url": "https://api.seerapi.com/v1/element_type_combination/111",
      "name": "混沌 冰"
    },
    {
      "id": 112,
      "url": "https://api.seerapi.com/v1/element_type_combination/112",
      "name": "自然 神秘"
    },
    {
      "id": 113,
      "url": "https://api.seerapi.com/v1/element_type_combination/113",
      "name": "虚空 邪灵"
    },
    {
      "id": 114,
      "url": "https://api.seerapi.com/v1/element_type_combination/114",
      "name": "虚空 混沌"
    },
    {
      "id": 115,
      "url": "https://api.seerapi.com/v1/element_type_combination/115",
      "name": "圣灵 轮回"
    },
    {
      "id": 116,
      "url": "https://api.seerapi.com/v1/element_type_combination/116",
      "name": "水 次元"
    },
    {
      "id": 117,
      "url": "https://api.seerapi.com/v1/element_type_combination/117",
      "name": "圣灵 神秘"
    },
    {
      "id": 118,
      "url": "https://api.seerapi.com/v1/element_type_combination/118",
      "name": "机械 神秘"
    },
    {
      "id": 119,
      "url": "https://api.seerapi.com/v1/element_type_combination/119",
      "name": "水 神秘"
    },
    {
      "id": 120,
      "url": "https://api.seerapi.com/v1/element_type_combination/120",
      "name": "次元 龙"
    },
    {
      "id": 121,
      "url": "https://api.seerapi.com/v1/element_type_combination/121",
      "name": "自然 超能"
    },
    {
      "id": 122,
      "url": "https://api.seerapi.com/v1/element_type_combination/122",
      "name": "电 机械"
    },
    {
      "id": 123,
      "url": "https://api.seerapi.com/v1/element_type_combination/123",
      "name": "神秘 轮回"
    },
    {
      "id": 124,
      "url": "https://api.seerapi.com/v1/element_type_combination/124",
      "name": "水 机械"
    },
    {
      "id": 125,
      "url": "https://api.seerapi.com/v1/element_type_combination/125",
      "name": "火 机械"
    },
    {
      "id": 126,
      "url": "https://api.seerapi.com/v1/element_type_combination/126",
      "name": "草 机械"
    },
    {
      "id": 127,
      "url": "https://api.seerapi.com/v1/element_type_combination/127",
      "name": "远古 电"
    },
    {
      "id": 128,
      "url": "https://api.seerapi.com/v1/element_type_combination/128",
      "name": "圣灵 飞行"
    },
    {
      "id": 129,
      "url": "https://api.seerapi.com/v1/element_type_combination/129",
      "name": "远古 机械"
    },
    {
      "id": 130,
      "url": "https://api.seerapi.com/v1/element_type_combination/130",
      "name": "远古 光"
    },
    {
      "id": 131,
      "url": "https://api.seerapi.com/v1/element_type_combination/131",
      "name": "混沌 光"
    },
    {
      "id": 132,
      "url": "https://api.seerapi.com/v1/element_type_combination/132",
      "name": "火 虫"
    },
    {
      "id": 221,
      "url": "https://api.seerapi.com/v1/element_type_combination/221",
      "name": "王"
    },
    {
      "id": 222,
      "url": "https://api.seerapi.com/v1/element_type_combination/222",
      "name": "混沌"
    },
    {
      "id": 223,
      "url": "https://api.seerapi.com/v1/element_type_combination/223",
      "name": "神灵"
    },
    {
      "id": 224,
      "url": "https://api.seerapi.com/v1/element_type_combination/224",
      "name": "轮回"
    },
    {
      "id": 225,
      "url": "https://api.seerapi.com/v1/element_type_combination/225",
      "name": "虫"
    },
    {
      "id": 226,
      "url": "https://api.seerapi.com/v1/element_type_combination/226",
      "name": "虚空"
    }
  ],
  "hash": "cd92d33d"
}