{
  "type": {
    "id": 3,
    "url": "https://api.seerapi.com/v1/mintmark_type/3"
  },
  "rarity": {
    "id": 2,
    "url": "https://api.seerapi.com/v1/mintmark_rarity/2"
  },
  "pet": null,
  "id": 41682,
  "name": "伪装祝福",
  "desc": "体力9/95,防御6/60,特防6/60",
  "mintmark_class": {
    "id": 40,
    "url": "https://api.seerapi.com/v1/mintmark_class/40"
  },
  "base_attr_value": {
    "atk": 0,
    "def": 6,
    "sp_atk": 0,
    "sp_def": 6,
    "spd": 0,
    "hp": 9,
    "percent": false,
    "total": 21
  },
  "max_attr_value": {
    "atk": 0,
    "def": 60,
    "sp_atk": 0,
    "sp_def": 60,
    "spd": 0,
    "hp": 95,
    "percent": false,
    "total": 215
  },
  "extra_attr_value": null,
  "connect": null,
  "is_hidden": false,
  "hash": "be53d1e0"
}