{
  "id": 986,
  "args_num": 1,
  "info": "先出手时造成的攻击伤害额外提升{0}%",
  "info_formatting_adjustment": null,
  "analyze_info": "[sprite name=iconHit]先出手时造成的攻击[color=#52a5f2]伤害额外提升[/color]{0}%",
  "pve_effective": false,
  "param": null,
  "skill": [
    {
      "id": 19746,
      "url": "https://api.seerapi.com/v1/skill/19746"
    },
    {
      "id": 19772,
      "url": "https://api.seerapi.com/v1/skill/19772"
    },
    {
      "id": 19799,
      "url": "https://api.seerapi.com/v1/skill/19799"
    },
    {
      "id": 30019,
      "url": "https://api.seerapi.com/v1/skill/30019"
    },
    {
      "id": 30133,
      "url": "https://api.seerapi.com/v1/skill/30133"
    },
    {
      "id": 30227,
      "url": "https://api.seerapi.com/v1/skill/30227"
    },
    {
      "id": 30251,
      "url": "https://api.seerapi.com/v1/skill/30251"
    },
    {
      "id": 30291,
      "url": "https://api.seerapi.com/v1/skill/30291"
    },
    {
      "id": 30392,
      "url": "https://api.seerapi.com/v1/skill/30392"
    },
    {
      "id": 30402,
      "url": "https://api.seerapi.com/v1/skill/30402"
    },
    {
      "id": 30452,
      "url": "https://api.seerapi.com/v1/skill/30452"
    },
    {
      "id": 30529,
      "url": "https://api.seerapi.com/v1/skill/30529"
    },
    {
      "id": 30606,
      "url": "https://api.seerapi.com/v1/skill/30606"
    },
    {
      "id": 30630,
      "url": "https://api.seerapi.com/v1/skill/30630"
    },
    {
      "id": 30662,
      "url": "https://api.seerapi.com/v1/skill/30662"
    },
    {
      "id": 30701,
      "url": "https://api.seerapi.com/v1/skill/30701"
    },
    {
      "id": 30808,
      "url": "https://api.seerapi.com/v1/skill/30808"
    },
    {
      "id": 30844,
      "url": "https://api.seerapi.com/v1/skill/30844"
    },
    {
      "id": 30968,
      "url": "https://api.seerapi.com/v1/skill/30968"
    },
    {
      "id": 30982,
      "url": "https://api.seerapi.com/v1/skill/30982"
    },
    {
      "id": 30990,
      "url": "https://api.seerapi.com/v1/skill/30990"
    },
    {
      "id": 31050,
      "url": "https://api.seerapi.com/v1/skill/31050"
    },
    {
      "id": 31078,
      "url": "https://api.seerapi.com/v1/skill/31078"
    },
    {
      "id": 31101,
      "url": "https://api.seerapi.com/v1/skill/31101"
    },
    {
      "id": 31192,
      "url": "https://api.seerapi.com/v1/skill/31192"
    },
    {
      "id": 31300,
      "url": "https://api.seerapi.com/v1/skill/31300"
    },
    {
      "id": 31412,
      "url": "https://api.seerapi.com/v1/skill/31412"
    },
    {
      "id": 31428,
      "url": "https://api.seerapi.com/v1/skill/31428"
    },
    {
      "id": 31611,
      "url": "https://api.seerapi.com/v1/skill/31611"
    },
    {
      "id": 31814,
      "url": "https://api.seerapi.com/v1/skill/31814"
    },
    {
      "id": 31875,
      "url": "https://api.seerapi.com/v1/skill/31875"
    },
    {
      "id": 32081,
      "url": "https://api.seerapi.com/v1/skill/32081"
    },
    {
      "id": 32324,
      "url": "https://api.seerapi.com/v1/skill/32324"
    },
    {
      "id": 32368,
      "url": "https://api.seerapi.com/v1/skill/32368"
    },
    {
      "id": 32414,
      "url": "https://api.seerapi.com/v1/skill/32414"
    },
    {
      "id": 32420,
      "url": "https://api.seerapi.com/v1/skill/32420"
    },
    {
      "id": 32426,
      "url": "https://api.seerapi.com/v1/skill/32426"
    },
    {
      "id": 32457,
      "url": "https://api.seerapi.com/v1/skill/32457"
    },
    {
      "id": 32488,
      "url": "https://api.seerapi.com/v1/skill/32488"
    },
    {
      "id": 32817,
      "url": "https://api.seerapi.com/v1/skill/32817"
    },
    {
      "id": 32891,
      "url": "https://api.seerapi.com/v1/skill/32891"
    },
    {
      "id": 33087,
      "url": "https://api.seerapi.com/v1/skill/33087"
    },
    {
      "id": 33304,
      "url": "https://api.seerapi.com/v1/skill/33304"
    },
    {
      "id": 33782,
      "url": "https://api.seerapi.com/v1/skill/33782"
    },
    {
      "id": 33876,
      "url": "https://api.seerapi.com/v1/skill/33876"
    },
    {
      "id": 34046,
      "url": "https://api.seerapi.com/v1/skill/34046"
    },
    {
      "id": 34165,
      "url": "https://api.seerapi.com/v1/skill/34165"
    },
    {
      "id": 34206,
      "url": "https://api.seerapi.com/v1/skill/34206"
    },
    {
      "id": 34289,
      "url": "https://api.seerapi.com/v1/skill/34289"
    },
    {
      "id": 34534,
      "url": "https://api.seerapi.com/v1/skill/34534"
    },
    {
      "id": 35170,
      "url": "https://api.seerapi.com/v1/skill/35170"
    },
    {
      "id": 35238,
      "url": "https://api.seerapi.com/v1/skill/35238"
    },
    {
      "id": 35388,
      "url": "https://api.seerapi.com/v1/skill/35388"
    },
    {
      "id": 35413,
      "url": "https://api.seerapi.com/v1/skill/35413"
    },
    {
      "id": 35576,
      "url": "https://api.seerapi.com/v1/skill/35576"
    },
    {
      "id": 35626,
      "url": "https://api.seerapi.com/v1/skill/35626"
    },
    {
      "id": 35676,
      "url": "https://api.seerapi.com/v1/skill/35676"
    },
    {
      "id": 35872,
      "url": "https://api.seerapi.com/v1/skill/35872"
    },
    {
      "id": 35877,
      "url": "https://api.seerapi.com/v1/skill/35877"
    },
    {
      "id": 35987,
      "url": "https://api.seerapi.com/v1/skill/35987"
    },
    {
      "id": 35999,
      "url": "https://api.seerapi.com/v1/skill/35999"
    },
    {
      "id": 36030,
      "url": "https://api.seerapi.com/v1/skill/36030"
    },
    {
      "id": 36158,
      "url": "https://api.seerapi.com/v1/skill/36158"
    },
    {
      "id": 36258,
      "url": "https://api.seerapi.com/v1/skill/36258"
    },
    {
      "id": 36394,
      "url": "https://api.seerapi.com/v1/skill/36394"
    },
    {
      "id": 36404,
      "url": "https://api.seerapi.com/v1/skill/36404"
    },
    {
      "id": 36667,
      "url": "https://api.seerapi.com/v1/skill/36667"
    },
    {
      "id": 36902,
      "url": "https://api.seerapi.com/v1/skill/36902"
    },
    {
      "id": 37219,
      "url": "https://api.seerapi.com/v1/skill/37219"
    },
    {
      "id": 38061,
      "url": "https://api.seerapi.com/v1/skill/38061"
    },
    {
      "id": 38063,
      "url": "https://api.seerapi.com/v1/skill/38063"
    },
    {
      "id": 38387,
      "url": "https://api.seerapi.com/v1/skill/38387"
    }
  ],
  "tag": [
    {
      "id": 18673,
      "url": "https://api.seerapi.com/v1/skill_effect_type_tag/18673"
    }
  ],
  "hash": "c2655613"
}