{
  "id": 1754,
  "args_num": 3,
  "info": "获得{0}点护盾，护盾消失时附加{1}点固定伤害同时使自身下{2}次攻击造成的伤害翻倍",
  "info_formatting_adjustment": "获得{0}点护盾\r\n--><condition>护盾消失时</condition>附加{1}点固定伤害同时使自身下{2}次攻击造成的伤害翻倍",
  "analyze_info": "[sprite name=iconHit]获得{0}点[color=#57c975]护盾[/color]，[color=#57c975]护盾[/color]消失时附加{1}点[color=#52a5f2]固定伤害[/color]同时使自身下{2}次攻击造成的伤害翻倍（boss有效）",
  "pve_effective": true,
  "param": null,
  "skill": [
    {
      "id": 25741,
      "url": "https://api.seerapi.com/v1/skill/25741"
    },
    {
      "id": 26113,
      "url": "https://api.seerapi.com/v1/skill/26113"
    },
    {
      "id": 26161,
      "url": "https://api.seerapi.com/v1/skill/26161"
    },
    {
      "id": 26252,
      "url": "https://api.seerapi.com/v1/skill/26252"
    },
    {
      "id": 26465,
      "url": "https://api.seerapi.com/v1/skill/26465"
    },
    {
      "id": 26537,
      "url": "https://api.seerapi.com/v1/skill/26537"
    },
    {
      "id": 26613,
      "url": "https://api.seerapi.com/v1/skill/26613"
    },
    {
      "id": 26632,
      "url": "https://api.seerapi.com/v1/skill/26632"
    },
    {
      "id": 26714,
      "url": "https://api.seerapi.com/v1/skill/26714"
    },
    {
      "id": 26923,
      "url": "https://api.seerapi.com/v1/skill/26923"
    },
    {
      "id": 27061,
      "url": "https://api.seerapi.com/v1/skill/27061"
    },
    {
      "id": 27324,
      "url": "https://api.seerapi.com/v1/skill/27324"
    },
    {
      "id": 27395,
      "url": "https://api.seerapi.com/v1/skill/27395"
    },
    {
      "id": 27431,
      "url": "https://api.seerapi.com/v1/skill/27431"
    },
    {
      "id": 28586,
      "url": "https://api.seerapi.com/v1/skill/28586"
    },
    {
      "id": 28955,
      "url": "https://api.seerapi.com/v1/skill/28955"
    },
    {
      "id": 29382,
      "url": "https://api.seerapi.com/v1/skill/29382"
    },
    {
      "id": 30894,
      "url": "https://api.seerapi.com/v1/skill/30894"
    },
    {
      "id": 33733,
      "url": "https://api.seerapi.com/v1/skill/33733"
    },
    {
      "id": 35341,
      "url": "https://api.seerapi.com/v1/skill/35341"
    }
  ],
  "tag": [
    {
      "id": 40695,
      "url": "https://api.seerapi.com/v1/skill_effect_type_tag/40695"
    },
    {
      "id": 60828,
      "url": "https://api.seerapi.com/v1/skill_effect_type_tag/60828"
    },
    {
      "id": 18673,
      "url": "https://api.seerapi.com/v1/skill_effect_type_tag/18673"
    }
  ],
  "hash": "c4f4a623"
}