{
  "data": {
    "41297": {
      "type": {
        "id": 3,
        "url": "https://api.seerapi.com/v1/mintmark_type/3"
      },
      "rarity": {
        "id": 1,
        "url": "https://api.seerapi.com/v1/mintmark_rarity/1"
      },
      "pet": [
        {
          "id": 3670,
          "url": "https://api.seerapi.com/v1/pet/3670"
        }
      ],
      "id": 41297,
      "name": "圣耀之光·黄金天马专属全能刻印",
      "desc": "体力7/76,特攻3/32,防御2/24,特防2/24,速度2/25",
      "mintmark_class": null,
      "base_attr_value": {
        "atk": 0,
        "def": 2,
        "sp_atk": 3,
        "sp_def": 2,
        "spd": 2,
        "hp": 7,
        "percent": false,
        "total": 16
      },
      "max_attr_value": {
        "atk": 0,
        "def": 24,
        "sp_atk": 32,
        "sp_def": 24,
        "spd": 25,
        "hp": 76,
        "percent": false,
        "total": 181
      },
      "extra_attr_value": null,
      "connect": null,
      "is_hidden": false
    }
  },
  "hash": "3a522e2b"
}