{
  "type": {
    "id": 0,
    "url": "https://api.seerapi.com/v1/mintmark_type/0"
  },
  "rarity": {
    "id": 1,
    "url": "https://api.seerapi.com/v1/mintmark_rarity/1"
  },
  "pet": [
    {
      "id": 309,
      "url": "https://api.seerapi.com/v1/pet/309"
    }
  ],
  "id": 10145,
  "name": "烈焰纹章",
  "desc": "攻击+10 防御+10 特攻+10 特防+10 体力+15 速度+5",
  "effect": null,
  "mintmark_class": null,
  "base_attr_value": null,
  "max_attr_value": {
    "atk": 10,
    "def": 10,
    "sp_atk": 10,
    "sp_def": 10,
    "spd": 15,
    "hp": 5,
    "percent": false,
    "total": 60
  },
  "extra_attr_value": null,
  "skill": null,
  "connect": null,
  "is_hidden": false,
  "hash": "d8046c4"
}