{
  "data": {
    "4096": {
      "id": 4096,
      "name": "月牙之刃",
      "yielding_exp": 130,
      "catch_rate": 0,
      "evolving_lv": 0,
      "releaseable": false,
      "fusion_master": false,
      "fusion_sub": false,
      "has_resistance": true,
      "resource_id": 4096,
      "enemy_resource_id": null,
      "type": {
        "id": 59,
        "url": "https://api.seerapi.com/v1/element_type_combination/59"
      },
      "gender": {
        "id": 1,
        "url": "https://api.seerapi.com/v1/pet_gender/1"
      },
      "base_stats": {
        "atk": 140,
        "def": 113,
        "sp_atk": 70,
        "sp_def": 112,
        "spd": 134,
        "hp": 166,
        "percent": false,
        "total": 735
      },
      "pet_class": {
        "id": 2756,
        "url": "https://api.seerapi.com/v1/pet_class/2756"
      },
      "evolution_chain_index": 0,
      "yielding_ev": {
        "atk": 1,
        "def": 0,
        "sp_atk": 0,
        "sp_def": 0,
        "spd": 1,
        "hp": 0,
        "percent": false,
        "total": 2
      },
      "vipbuff": null,
      "mount_type": null,
      "diy_stats": null,
      "skill": [
        {
          "learning_level": 1,
          "is_special": false,
          "is_advanced": false,
          "is_fifth": false,
          "skill": {
            "id": 10499,
            "url": "https://api.seerapi.com/v1/skill/10499"
          },
          "skill_activation_item": null
        },
        {
          "learning_level": 5,
          "is_special": false,
          "is_advanced": false,
          "is_fifth": false,
          "skill": {
            "id": 20030,
            "url": "https://api.seerapi.com/v1/skill/20030"
          },
          "skill_activation_item": null
        },
        {
          "learning_level": 9,
          "is_special": false,
          "is_advanced": false,
          "is_fifth": false,
          "skill": {
            "id": 11077,
            "url": "https://api.seerapi.com/v1/skill/11077"
          },
          "skill_activation_item": null
        },
        {
          "learning_level": 13,
          "is_special": false,
          "is_advanced": false,
          "is_fifth": false,
          "skill": {
            "id": 10629,
            "url": "https://api.seerapi.com/v1/skill/10629"
          },
          "skill_activation_item": null
        },
        {
          "learning_level": 17,
          "is_special": false,
          "is_advanced": false,
          "is_fifth": false,
          "skill": {
            "id": 20454,
            "url": "https://api.seerapi.com/v1/skill/20454"
          },
          "skill_activation_item": null
        },
        {
          "learning_level": 21,
          "is_special": false,
          "is_advanced": false,
          "is_fifth": false,
          "skill": {
            "id": 34439,
            "url": "https://api.seerapi.com/v1/skill/34439"
          },
          "skill_activation_item": null
        },
        {
          "learning_level": 25,
          "is_special": false,
          "is_advanced": false,
          "is_fifth": false,
          "skill": {
            "id": 10637,
            "url": "https://api.seerapi.com/v1/skill/10637"
          },
          "skill_activation_item": null
        },
        {
          "learning_level": 29,
          "is_special": false,
          "is_advanced": false,
          "is_fifth": false,
          "skill": {
            "id": 20158,
            "url": "https://api.seerapi.com/v1/skill/20158"
          },
          "skill_activation_item": null
        },
        {
          "learning_level": 33,
          "is_special": false,
          "is_advanced": false,
          "is_fifth": false,
          "skill": {
            "id": 11782,
            "url": "https://api.seerapi.com/v1/skill/11782"
          },
          "skill_activation_item": null
        },
        {
          "learning_level": 37,
          "is_special": false,
          "is_advanced": false,
          "is_fifth": false,
          "skill": {
            "id": 34440,
            "url": "https://api.seerapi.com/v1/skill/34440"
          },
          "skill_activation_item": null
        },
        {
          "learning_level": 41,
          "is_special": false,
          "is_advanced": false,
          "is_fifth": false,
          "skill": {
            "id": 27277,
            "url": "https://api.seerapi.com/v1/skill/27277"
          },
          "skill_activation_item": null
        },
        {
          "learning_level": 45,
          "is_special": false,
          "is_advanced": false,
          "is_fifth": false,
          "skill": {
            "id": 34441,
            "url": "https://api.seerapi.com/v1/skill/34441"
          },
          "skill_activation_item": null
        },
        {
          "learning_level": 49,
          "is_special": false,
          "is_advanced": false,
          "is_fifth": false,
          "skill": {
            "id": 27278,
            "url": "https://api.seerapi.com/v1/skill/27278"
          },
          "skill_activation_item": null
        },
        {
          "learning_level": 53,
          "is_special": false,
          "is_advanced": false,
          "is_fifth": false,
          "skill": {
            "id": 34442,
            "url": "https://api.seerapi.com/v1/skill/34442"
          },
          "skill_activation_item": null
        },
        {
          "learning_level": 57,
          "is_special": false,
          "is_advanced": false,
          "is_fifth": false,
          "skill": {
            "id": 27279,
            "url": "https://api.seerapi.com/v1/skill/27279"
          },
          "skill_activation_item": null
        },
        {
          "learning_level": 61,
          "is_special": false,
          "is_advanced": false,
          "is_fifth": false,
          "skill": {
            "id": 34443,
            "url": "https://api.seerapi.com/v1/skill/34443"
          },
          "skill_activation_item": null
        },
        {
          "learning_level": 71,
          "is_special": false,
          "is_advanced": false,
          "is_fifth": true,
          "skill": {
            "id": 34444,
            "url": "https://api.seerapi.com/v1/skill/34444"
          },
          "skill_activation_item": null
        }
      ],
      "soulmark": [
        {
          "id": 1336,
          "url": "https://api.seerapi.com/v1/soulmark/1336"
        },
        {
          "id": 2112,
          "url": "https://api.seerapi.com/v1/soulmark/2112"
        }
      ],
      "encyclopedia_entry": {
        "id": 4096,
        "url": "https://api.seerapi.com/v1/pet_encyclopedia_entry/4096"
      },
      "archive_story_entry": {
        "id": 341,
        "url": "https://api.seerapi.com/v1/pet_archive_story_entry/341"
      },
      "peak_pool": null,
      "peak_expert_pool": null,
      "advance": null
    }
  },
  "hash": "d7f69031"
}