{
  "id": 2508,
  "args_num": 3,
  "info": "消除对手回合类效果并{0}%令自身{1}，触发成功则额外令对手{2}",
  "info_formatting_adjustment": "消除对手回合类效果并{0}%令自身{1}\r\n--><condition>触发成功</condition>则额外令对手{2}",
  "analyze_info": "",
  "pve_effective": false,
  "param": [
    {
      "position": 1,
      "param": {
        "id": 1,
        "url": "https://api.seerapi.com/v1/skill_effect_param/1"
      }
    },
    {
      "position": 2,
      "param": {
        "id": 1,
        "url": "https://api.seerapi.com/v1/skill_effect_param/1"
      }
    }
  ],
  "skill": [],
  "tag": [
    {
      "id": 30442,
      "url": "https://api.seerapi.com/v1/skill_effect_type_tag/30442"
    },
    {
      "id": 813,
      "url": "https://api.seerapi.com/v1/skill_effect_type_tag/813"
    }
  ],
  "hash": "5ca82578"
}