{
  "data": {
    "20689": {
      "type": {
        "id": 1,
        "url": "https://api.seerapi.com/v1/mintmark_type/1"
      },
      "rarity": {
        "id": 1,
        "url": "https://api.seerapi.com/v1/mintmark_rarity/1"
      },
      "pet": [
        {
          "id": 2878,
          "url": "https://api.seerapi.com/v1/pet/2878"
        }
      ],
      "id": 20689,
      "name": "化羽无极刻印",
      "desc": "回合数+1",
      "effect": {
        "effect": 107,
        "arg": 1
      },
      "mintmark_class": null,
      "base_attr_value": null,
      "max_attr_value": null,
      "extra_attr_value": null,
      "skill": [
        {
          "id": 24354,
          "url": "https://api.seerapi.com/v1/skill/24354"
        }
      ],
      "connect": null,
      "is_hidden": false
    }
  },
  "hash": "a23c2ff7"
}