{
  "data": {
    "40948": {
      "type": {
        "id": 3,
        "url": "https://api.seerapi.com/v1/mintmark_type/3"
      },
      "rarity": {
        "id": 2,
        "url": "https://api.seerapi.com/v1/mintmark_rarity/2"
      },
      "pet": null,
      "id": 40948,
      "name": "泰坦之魂αS",
      "desc": "体力80/80,特攻40/40,防御25/25,特防25/25,速度30/30",
      "effect": null,
      "mintmark_class": {
        "id": 17,
        "url": "https://api.seerapi.com/v1/mintmark_class/17"
      },
      "base_attr_value": {
        "atk": 0,
        "def": 25,
        "sp_atk": 40,
        "sp_def": 25,
        "spd": 30,
        "hp": 80,
        "percent": false,
        "total": 200
      },
      "max_attr_value": {
        "atk": 0,
        "def": 25,
        "sp_atk": 40,
        "sp_def": 25,
        "spd": 30,
        "hp": 80,
        "percent": false,
        "total": 200
      },
      "extra_attr_value": {
        "atk": 0,
        "def": 3,
        "sp_atk": 5,
        "sp_def": 3,
        "spd": 3,
        "hp": 6,
        "percent": false,
        "total": 20
      },
      "skill": null,
      "connect": null,
      "is_hidden": false
    }
  },
  "hash": "1ef7045c"
}