{
  "data": {
    "20467": {
      "type": {
        "id": 1,
        "url": "https://api.seerapi.com/v1/mintmark_type/1"
      },
      "rarity": {
        "id": 1,
        "url": "https://api.seerapi.com/v1/mintmark_rarity/1"
      },
      "pet": [
        {
          "id": 1842,
          "url": "https://api.seerapi.com/v1/pet/1842"
        }
      ],
      "id": 20467,
      "name": "无尽光芒刻印",
      "desc": "恢复效果提升至1/1",
      "effect": {
        "effect": 125,
        "arg": 1
      },
      "mintmark_class": null,
      "base_attr_value": null,
      "max_attr_value": null,
      "extra_attr_value": null,
      "skill": [
        {
          "id": 22371,
          "url": "https://api.seerapi.com/v1/skill/22371"
        }
      ],
      "connect": null,
      "is_hidden": false
    }
  },
  "hash": "8a61c4e0"
}