{
  "type": {
    "id": 3,
    "url": "https://api.seerapi.com/v1/mintmark_type/3"
  },
  "rarity": {
    "id": 1,
    "url": "https://api.seerapi.com/v1/mintmark_rarity/1"
  },
  "pet": [
    {
      "id": 4078,
      "url": "https://api.seerapi.com/v1/pet/4078"
    }
  ],
  "id": 41859,
  "name": "喋血·哀影疾风专属全能刻印",
  "desc": "体力7/75,特攻3/38,防御2/25,特防2/25,速度3/30",
  "effect": null,
  "mintmark_class": null,
  "base_attr_value": {
    "atk": 0,
    "def": 2,
    "sp_atk": 3,
    "sp_def": 2,
    "spd": 3,
    "hp": 7,
    "percent": false,
    "total": 17
  },
  "max_attr_value": {
    "atk": 0,
    "def": 25,
    "sp_atk": 38,
    "sp_def": 25,
    "spd": 30,
    "hp": 75,
    "percent": false,
    "total": 193
  },
  "extra_attr_value": null,
  "skill": null,
  "connect": null,
  "is_hidden": false,
  "hash": "a1851463"
}