{
  "type": {
    "id": 3,
    "url": "https://api.seerapi.com/v1/mintmark_type/3"
  },
  "rarity": {
    "id": 3,
    "url": "https://api.seerapi.com/v1/mintmark_rarity/3"
  },
  "pet": null,
  "id": 42489,
  "name": "空夜传说",
  "desc": "防御4/41,特攻2/25,特防4/41,速度2/25,体力8/88",
  "effect": null,
  "mintmark_class": {
    "id": 83,
    "url": "https://api.seerapi.com/v1/mintmark_class/83"
  },
  "base_attr_value": {
    "atk": 0,
    "def": 4,
    "sp_atk": 2,
    "sp_def": 4,
    "spd": 2,
    "hp": 8,
    "percent": false,
    "total": 20
  },
  "max_attr_value": {
    "atk": 0,
    "def": 41,
    "sp_atk": 25,
    "sp_def": 41,
    "spd": 25,
    "hp": 88,
    "percent": false,
    "total": 220
  },
  "extra_attr_value": {
    "atk": 0,
    "def": 5,
    "sp_atk": 0,
    "sp_def": 5,
    "spd": 0,
    "hp": 5,
    "percent": false,
    "total": 15
  },
  "skill": null,
  "connect": null,
  "is_hidden": false,
  "hash": "4f3778cd"
}