{
  "data": {
    "49": {
      "id": 49,
      "name": "四九系列",
      "mintmark": [
        {
          "id": 41739,
          "url": "https://api.seerapi.com/v1/mintmark/41739"
        },
        {
          "id": 41740,
          "url": "https://api.seerapi.com/v1/mintmark/41740"
        },
        {
          "id": 42210,
          "url": "https://api.seerapi.com/v1/mintmark/42210"
        },
        {
          "id": 42211,
          "url": "https://api.seerapi.com/v1/mintmark/42211"
        },
        {
          "id": 42699,
          "url": "https://api.seerapi.com/v1/mintmark/42699"
        },
        {
          "id": 42700,
          "url": "https://api.seerapi.com/v1/mintmark/42700"
        }
      ]
    }
  },
  "hash": "e57e9f11"
}